vda/__init__.py
vda/client/__init__.py
vda/client/cli.py
vda/cn_agent/__init__.py
vda/cn_agent/launcher.py
vda/cn_agent/syncup.py
vda/common/__init__.py
vda/common/cn_agent_schema.py
vda/common/constant.py
vda/common/dn_agent_schema.py
vda/common/modules.py
vda/common/name_fmt.py
vda/common/operation_client.py
vda/common/portal_schema.py
vda/common/spdk_client.py
vda/common/syncup.py
vda/common/utils.py
vda/database/__init__.py
vda/dn_agent/__init__.py
vda/dn_agent/launcher.py
vda/dn_agent/syncup.py
vda/grpc/__init__.py
vda/grpc/cn_agent_pb2.py
vda/grpc/cn_agent_pb2_grpc.py
vda/grpc/dn_agent_pb2.py
vda/grpc/dn_agent_pb2_grpc.py
vda/grpc/monitor_pb2.py
vda/grpc/monitor_pb2_grpc.py
vda/grpc/portal_pb2.py
vda/grpc/portal_pb2_grpc.py
vda/monitor/__init__.py
vda/monitor/basic_handler.py
vda/monitor/heartbeat_handler.py
vda/monitor/launcher.py
vda/monitor/syncup_handler.py
vda/portal/__init__.py
vda/portal/controller_node.py
vda/portal/disk_array.py
vda/portal/disk_node.py
vda/portal/exporter.py
vda/portal/launcher.py
vda/portal/manual_syncup.py
vda/portal/physical_disk.py
vda-0.0.5.dist-info/LICENSE.txt
vda-0.0.5.dist-info/METADATA
vda-0.0.5.dist-info/WHEEL
vda-0.0.5.dist-info/entry_points.txt
vda-0.0.5.dist-info/top_level.txt
vda-0.0.5.dist-info/RECORD
